django_workflow_activity-1.1.0.dist-info/DESCRIPTION.rst
django_workflow_activity-1.1.0.dist-info/METADATA
django_workflow_activity-1.1.0.dist-info/RECORD
django_workflow_activity-1.1.0.dist-info/WHEEL
django_workflow_activity-1.1.0.dist-info/metadata.json
django_workflow_activity-1.1.0.dist-info/top_level.txt
workflow_activity/__init__.py
workflow_activity/admin.py
workflow_activity/managers.py
workflow_activity/models.py
workflow_activity/utils.py
workflow_activity/migrations/0001_initial.py
workflow_activity/migrations/__init__.py
