Metadata-Version: 2.0
Name: django-workflow-activity
Version: 1.1.0
Summary: Manage all events on workflows
Home-page: https://github.com/unistra/django-workflow-activity
Author: Arnaud Grausem
Author-email: arnaud.grausem@unistra.fr
License: UNKNOWN
Keywords: workflows django events log
Platform: UNKNOWN
Classifier: Development Status :: 5 - Production/Stable
Classifier: Environment :: Web Environment
Classifier: Framework :: Django
Classifier: Intended Audience :: Developers
Classifier: Natural Language :: English
Classifier: Operating System :: POSIX :: Linux
Classifier: Programming Language :: Python :: 2.7
Classifier: Topic :: Internet :: WWW/HTTP :: WSGI :: Application
Requires-Dist: django-workflows-unistra
